cata/__init__.py
cata/__meta__.py
cata/tests.py
cata-0.1.0.dist-info/METADATA
cata-0.1.0.dist-info/WHEEL
cata-0.1.0.dist-info/top_level.txt
cata-0.1.0.dist-info/RECORD
