Metadata-Version: 2.1
Name: cata
Version: 0.1.0
Summary: cata is a dataset management platform for Python and R
Home-page: https://catalog-data.readthedocs.io
Author: Ian Dennis Miller
Author-email: ian@iandennismiller.com
License: MIT
Platform: UNKNOWN
Requires-Dist: mr.bob (==0.1.2)
